tcrhelloworld/__init__.py
tcrhelloworld/__main__.py
tcrhelloworld-0.1.3.dist-info/LICENSE
tcrhelloworld-0.1.3.dist-info/METADATA
tcrhelloworld-0.1.3.dist-info/WHEEL
tcrhelloworld-0.1.3.dist-info/entry_points.txt
tcrhelloworld-0.1.3.dist-info/top_level.txt
tcrhelloworld-0.1.3.dist-info/RECORD
