Metadata-Version: 2.1
Name: tcrhelloworld
Version: 0.1.3
Summary: simples example in the python world
Home-page: UNKNOWN
Author: TheCloudRecipes
Author-email: thecloudrecipes@gmail.com
License: MIT
Platform: UNKNOWN
